{"date_folder":"1781-05", "time":40,"annotations":[{"start":52,"end":56,"spot":"Bono","confidence":0.7038,"id":109350,"title":"Bono","uri":"http://de.wikipedia.org/wiki/Bono","label":"Bono","categories":["Bono","Echo-Pop-Preisträger","Ehrenbürger von Dublin","Ehrendoktor der Keiō-Universität","Ehrendoktor der University of Pennsylvania","Geboren 1960","Golden-Globe-Preisträger","Grammy-Preisträger","Honorary Knight Commander des Order of the British Empire","Ire","Mann","Mitglied der American Academy of Arts and Sciences","Mitglied der Ehrenlegion (Ritter)","Musiker (Irland)","Pseudonym","Rocksänger","Träger des Ivor Novello Award","Träger des Ordens der Freiheit","Träger des Ordre des Arts et des Lettres (Komtur)","U2 (Band)"],"types":["http://dbpedia.org/ontology/Person","http://dbpedia.org/ontology/Species","http://dbpedia.org/ontology/Eukaryote","http://dbpedia.org/ontology/Animal"],"alternateLabels":["Bono"]},{"start":60,"end":69,"spot":"Belgirate","confidence":0.8609,"id":963292,"title":"Belgirate","uri":"http://de.wikipedia.org/wiki/Belgirate","label":"Belgirate","categories":["Ort als Namensgeber für einen Asteroiden","Ort im Piemont"],"types":["http://dbpedia.org/ontology/Settlement","http://dbpedia.org/ontology/PopulatedPlace","http://dbpedia.org/ontology/Place","http://dbpedia.org/ontology/Location"],"alternateLabels":["Belgirate"]},{"start":86,"end":94,"spot":"Stähelin","confidence":0.7647,"id":6950701,"title":"Felix Staehelin","uri":"http://de.wikipedia.org/wiki/Felix_Staehelin","label":"Felix Staehelin","categories":["Althistoriker","Geboren 1873","Gestorben 1952","Hochschullehrer (Universität Basel)","Mann","Mitglied der Akademie der Wissenschaften der DDR","Mitglied der Preußischen Akademie der Wissenschaften","Sachbuchautor","Schweizer"],"types":["http://dbpedia.org/ontology/Person","http://dbpedia.org/ontology/Species","http://dbpedia.org/ontology/Eukaryote","http://dbpedia.org/ontology/Animal"],"alternateLabels":["Felix Staehelin","Felix Stähelin"]},{"start":100,"end":105,"spot":"Basel","confidence":0.7444,"id":8509,"title":"Basel","uri":"http://de.wikipedia.org/wiki/Basel","label":"Basel","categories":["Basel","Hauptort eines Kantons (Schweiz)","Hochschul- oder Universitätsstadt in der Schweiz","Ort am Hochrhein","Ort am Oberrhein","Ort an der Wiese","Ort im Kanton Basel-Stadt","Ort mit Binnenhafen","Ortsbild von nationaler Bedeutung im Kanton Basel-Stadt","Reichsstadt","Schweizer Gemeinde","Stadt als Namensgeber für einen Asteroiden","Stadtrechtsverleihung 1264"],"types":["http://dbpedia.org/ontology/Settlement","http://dbpedia.org/ontology/PopulatedPlace","http://dbpedia.org/ontology/Place","http://dbpedia.org/ontology/Location"],"alternateLabels":["Basel","Basler","Stadt Basel","Basel-Gasfabrik","Bâle"]},{"start":130,"end":140,"spot":"Versailles","confidence":0.7508,"id":15255,"title":"Versailles","uri":"http://de.wikipedia.org/wiki/Versailles","label":"Versailles","categories":["Ehemalige Hauptstadt (Frankreich)","Hochschul- oder Universitätsstadt in Frankreich","Ort in der Île-de-France","Präfektur in Frankreich","Stadt als Namensgeber für einen Asteroiden","Stadt in Frankreich","Versailles"],"types":["http://dbpedia.org/ontology/Settlement","http://dbpedia.org/ontology/PopulatedPlace","http://dbpedia.org/ontology/Place","http://dbpedia.org/ontology/Location"],"alternateLabels":["Versailles","Versailler","Versailles-Chantiers"]},{"start":164,"end":171,"spot":"Zurzach","confidence":0.7967,"id":367732,"title":"Bad Zurzach","uri":"http://de.wikipedia.org/wiki/Bad_Zurzach","label":"Bad Zurzach","categories":["Ehemalige politische Gemeinde in der Schweiz","Ersterwähnung 830","Gemeindeauflösung 2021","Geographie (Zurzach)","Heilbad","Kurort im Kanton Aargau","Ort am Hochrhein","Ort im Kanton Aargau","Ortsbild von nationaler Bedeutung im Kanton Aargau"],"types":["http://dbpedia.org/ontology/Settlement","http://dbpedia.org/ontology/PopulatedPlace","http://dbpedia.org/ontology/Place","http://dbpedia.org/ontology/Location"],"alternateLabels":["Bad Zurzach","Zurzach","Tenedo"]},{"start":186,"end":200,"spot":"von Blumenthal","confidence":0.7016,"id":376387,"title":"Leonhard von Blumenthal","uri":"http://de.wikipedia.org/wiki/Leonhard_von_Blumenthal","label":"Leonhard von Blumenthal","categories":["Deutscher","Ehrenbürger von Düsseldorf","Ehrenbürger von Halle (Saale)","Ehrenbürger von Magdeburg","Familienmitglied des Adelsgeschlechts Blumenthal","Geboren 1810","Generalfeldmarschall (Preußen)","Gestorben 1900","Großkomtur des Königlichen Hausordens von Hohenzollern","Großkreuz des Hausordens der Wendischen Krone","Inhaber des Fürstlichen Hausordens von Hohenzollern (I. Klasse)","Mann","Person im Deutsch-Französischen Krieg","Person im Deutschen Krieg","Person in der Schleswig-Holsteinischen Erhebung (Preußen)","Ritter des Ordens Pour le Mérite mit Eichenlaub","Ritter des Schwarzen Adlerordens","Titulargraf","Träger des Bayerischen Militärverdienstordens (Großkreuz)","Träger des Eisernen Kreuzes I. Klasse","Träger des Großkreuzes des Roten Adlerordens","Träger des Hubertusordens","Träger des Militär-Karl-Friedrich-Verdienstordens (Komtur)","Träger des Militär-Max-Joseph-Ordens (Komtur)","Träger des Ordens der Heiligen Anna","Träger des Seraphinenordens","Träger des Württembergischen Militärverdienstordens (Großkreuz)","Träger des k.u. Sankt Stephans-Ordens (Großkreuz)","Träger des ö.k. Leopold-Ordens (Großkreuz)"],"types":["http://dbpedia.org/ontology/Person","http://dbpedia.org/ontology/Species","http://dbpedia.org/ontology/Eukaryote","http://dbpedia.org/ontology/Animal"],"alternateLabels":["Leonhard von Blumenthal","Graf Blumenthal","Leonhard Graf von Blumenthal","Von Blumenthal"]},{"start":225,"end":234,"spot":"Solothurn","confidence":0.8092,"id":995981,"title":"Solothurn","uri":"http://de.wikipedia.org/wiki/Solothurn","label":"Solothurn","categories":["Hauptort eines Kantons (Schweiz)","Ort an der Aare","Ort im Kanton Solothurn","Ortsbild von nationaler Bedeutung im Kanton Solothurn","Ortsname keltischer Herkunft","Reichsstadt","Schweizer Gemeinde","Solothurn"],"types":["http://dbpedia.org/ontology/Settlement","http://dbpedia.org/ontology/PopulatedPlace","http://dbpedia.org/ontology/Place","http://dbpedia.org/ontology/Location"],"alternateLabels":["Solothurn","Salodurum","Stadt Solothurn","Solothurnischen"]},{"start":344,"end":349,"spot":"Paris","confidence":0.7793,"id":11446,"title":"Paris","uri":"http://de.wikipedia.org/wiki/Paris","label":"Paris","categories":["Französisches Département","Hauptstadt einer französischen Region","Hauptstadt in Europa","Hauptstadt in der EU","Hochschul- oder Universitätsstadt in Frankreich","Millionenstadt","Mitglied der Ehrenlegion (Stadt)","Namensgeber für ein chemisches Element","Ort an der Seine","Ort in der Île-de-France","Ortsname keltischer Herkunft","Paris","Präfektur in Frankreich","Träger des Croix de guerre 1914–1918 (Ort in Frankreich)","Träger des Ordre de la Libération"],"types":["http://dbpedia.org/ontology/Settlement","http://dbpedia.org/ontology/PopulatedPlace","http://dbpedia.org/ontology/Place","http://dbpedia.org/ontology/Location"],"alternateLabels":["Paris","Pariser","Hauptstadt","Département Paris","Hauptstadtklub"]},{"start":351,"end":359,"spot":"Pelegrin","confidence":0.6976,"id":12289852,"title":"Marta Pelegrín","uri":"http://de.wikipedia.org/wiki/Marta_Pelegr%C3%ADn","label":"Marta Pelegrín","types":[],"alternateLabels":["Marta Pelegrín"]},{"start":374,"end":378,"spot":"Lyon","confidence":0.8032,"id":13964,"title":"Lyon","uri":"http://de.wikipedia.org/wiki/Lyon","label":"Lyon","categories":["Hauptstadt einer französischen Region","Hochschul- oder Universitätsstadt in Frankreich","Lyon","Mitglied der Ehrenlegion (Stadt)","Ort an der Rhone","Ort an der Saône","Ort in Auvergne-Rhône-Alpes","Präfektur in Frankreich","Stadt als Namensgeber für einen Asteroiden","Stadt in Frankreich","Welterbestätte in Europa","Welterbestätte in Frankreich","Weltkulturerbestätte"],"types":["http://dbpedia.org/ontology/Settlement","http://dbpedia.org/ontology/PopulatedPlace","http://dbpedia.org/ontology/Place","http://dbpedia.org/ontology/Location"],"alternateLabels":["Lyon","Lugdunum","Lugudunum","Lyon-Mouche","Lyoner"]},{"start":380,"end":387,"spot":"Hausler","confidence":0.7796,"id":278308,"title":"Häusler","uri":"http://de.wikipedia.org/wiki/H%C3%A4usler","label":"Häusler","categories":["Agrarrechtsgeschichte","Agrarsoziologie"],"types":[],"alternateLabels":["Häusler","Brinksitzer","Köbler","Podsedeken","Kleinhäusler"]},{"start":389,"end":391,"spot":"Hr","confidence":0.6591,"id":2768,"title":"Kroatien","uri":"http://de.wikipedia.org/wiki/Kroatien","label":"Kroatien","categories":["Kroatien","Mitglied des Europarats","Mitgliedstaat der Europäischen Union","Mitgliedstaat der NATO","Mitgliedstaat der Vereinten Nationen","Staat in Europa","Verwaltungseinheit als Namensgeber für einen Asteroiden"],"types":["http://dbpedia.org/ontology/Country","http://dbpedia.org/ontology/PopulatedPlace","http://dbpedia.org/ontology/Place","http://dbpedia.org/ontology/Location"],"alternateLabels":["Kroatien","Kroatischer","Kroatischen","Kroatische","Kroatisch"]},{"start":393,"end":397,"spot":"Maas","confidence":0.7686,"id":14674,"title":"Maas","uri":"http://de.wikipedia.org/wiki/Maas","label":"Maas","categories":["Ardennen","Fluss in Belgien","Gewässer als Namensgeber für einen Asteroiden","Gewässername keltischer Herkunft","Grenze zwischen Belgien und den Niederlanden","Grenzfluss"],"types":["http://dbpedia.org/ontology/River","http://dbpedia.org/ontology/Stream","http://dbpedia.org/ontology/Place","http://dbpedia.org/ontology/NaturalPlace","http://dbpedia.org/ontology/Location","http://dbpedia.org/ontology/BodyOfWater"],"alternateLabels":["Maas","Meuse","Mouze"]},{"start":402,"end":407,"spot":"Basel","confidence":0.746,"id":8509,"title":"Basel","uri":"http://de.wikipedia.org/wiki/Basel","label":"Basel","categories":["Basel","Hauptort eines Kantons (Schweiz)","Hochschul- oder Universitätsstadt in der Schweiz","Ort am Hochrhein","Ort am Oberrhein","Ort an der Wiese","Ort im Kanton Basel-Stadt","Ort mit Binnenhafen","Ortsbild von nationaler Bedeutung im Kanton Basel-Stadt","Reichsstadt","Schweizer Gemeinde","Stadt als Namensgeber für einen Asteroiden","Stadtrechtsverleihung 1264"],"types":["http://dbpedia.org/ontology/Settlement","http://dbpedia.org/ontology/PopulatedPlace","http://dbpedia.org/ontology/Place","http://dbpedia.org/ontology/Location"],"alternateLabels":["Basel","Basler","Stadt Basel","Basel-Gasfabrik","Bâle"]},{"start":437,"end":445,"spot":"Auvergne","confidence":0.7054,"id":85774,"title":"Auvergne","uri":"http://de.wikipedia.org/wiki/Auvergne","label":"Auvergne","categories":["Aufgelöst 2015","Ehemalige französische Region","Geschichte (Auvergne-Rhône-Alpes)","Verwaltungseinheit als Namensgeber für einen Asteroiden"],"types":["http://dbpedia.org/ontology/Place","http://dbpedia.org/ontology/Location"],"alternateLabels":["Auvergne","Auvergnatischen","Basse-Auvergne","FR-C"]},{"start":452,"end":457,"spot":"Zobel","confidence":0.7222,"id":5966376,"title":"Zobelfell","uri":"http://de.wikipedia.org/wiki/Zobelfell","label":"Zobelfell","categories":["Pelzart"],"types":[],"alternateLabels":["Zobelfell","Zobel","Zobelpelz"]},{"start":513,"end":518,"spot":"ADLER","confidence":0.6364,"id":106219,"title":"Adler (Wappentier)","uri":"http://de.wikipedia.org/wiki/Adler_%28Wappentier%29","label":"Adler","categories":["Adler (Wappentier)","Wappentier"],"types":[],"alternateLabels":["Adler","Adlers","Adlerkopf","Adlern","Preußischen Adler"]},{"start":541,"end":549,"spot":"ROTHHAUS","confidence":0.7808,"id":5000952,"title":"Rothhaus","uri":"http://de.wikipedia.org/wiki/Rothhaus","label":"Rothhaus","categories":["Gemeinde Comprachtschütz","Ort der Woiwodschaft Opole","Ort in Schlesien"],"types":["http://dbpedia.org/ontology/Settlement","http://dbpedia.org/ontology/PopulatedPlace","http://dbpedia.org/ontology/Place","http://dbpedia.org/ontology/Location"],"alternateLabels":["Rothhaus","Osiny"]},{"start":580,"end":585,"spot":"Mylan","confidence":0.8641,"id":3535721,"title":"Mylan (Unternehmen)","uri":"http://de.wikipedia.org/wiki/Mylan_%28Unternehmen%29","label":"Mylan","categories":["Gegründet 1961","Pharmazieunternehmen","Produzierendes Unternehmen (Niederlande)","Unternehmen (Amsterdam)"],"types":["http://dbpedia.org/ontology/Company","http://dbpedia.org/ontology/Organisation","http://dbpedia.org/ontology/Agent"],"alternateLabels":["Mylan","Mylan Laboratories"]},{"start":617,"end":624,"spot":"Sachsen","confidence":0.6742,"id":25025,"title":"Sachsen","uri":"http://de.wikipedia.org/wiki/Sachsen","label":"Sachsen","categories":["Bundesland (Deutschland)","Land der Weimarer Republik","Mitteldeutschland","Sachsen","Verwaltungseinheit als Namensgeber für einen Asteroiden"],"types":["http://dbpedia.org/ontology/Place","http://dbpedia.org/ontology/Location"],"alternateLabels":["Sachsen","Sächsischen","Freistaat Sachsen","Freistaates Sachsen","Sächsische"]},{"start":651,"end":660,"spot":"Weiningen","confidence":0.826,"id":870073,"title":"Weiningen ZH","uri":"http://de.wikipedia.org/wiki/Weiningen_ZH","label":"Weiningen ZH","categories":["Ersterwähnung 870","Ort im Kanton Zürich","Schweizer Gemeinde","Weiningen ZH"],"types":["http://dbpedia.org/ontology/Settlement","http://dbpedia.org/ontology/PopulatedPlace","http://dbpedia.org/ontology/Place","http://dbpedia.org/ontology/Location"],"alternateLabels":["Weiningen","Weiningen ZH"]},{"start":671,"end":677,"spot":"Böhmen","confidence":0.7772,"id":614,"title":"Böhmen","uri":"http://de.wikipedia.org/wiki/B%C3%B6hmen","label":"Böhmen","categories":["Böhmen","Geographisches Objekt als Namensgeber für einen Asteroiden","Historische Landschaft oder Region in Europa","Historisches Territorium (Tschechien)","Region in Europa","Österreichisches Kronland"],"types":[],"alternateLabels":["Böhmen","Böhmischen","Böhmischer","Böhmische","Königreich Böhmen"]},{"start":758,"end":763,"spot":"Landl","confidence":0.8039,"id":999054,"title":"Landl","uri":"http://de.wikipedia.org/wiki/Landl","label":"Landl","categories":["Eisenwurzen","Ennstaler Alpen","Gemeindegründung 2015","Hochschwab","Katastralgemeinde im Bezirk Liezen","Ort an der Enns","Salza (Enns)","Ybbstaler Alpen"],"types":["http://dbpedia.org/ontology/Settlement","http://dbpedia.org/ontology/PopulatedPlace","http://dbpedia.org/ontology/Place","http://dbpedia.org/ontology/Location"],"alternateLabels":["Landl"]},{"start":822,"end":835,"spot":"von Güttingen","confidence":0.7243,"id":5564571,"title":"Rudolf von Güttingen","uri":"http://de.wikipedia.org/wiki/Rudolf_von_G%C3%BCttingen","label":"Rudolf von Güttingen","categories":["Abt (St. Gallen)","Bischof von Chur","Geboren im 12. Jahrhundert","Gestorben 1226","Mann","Römisch-katholischer Bischof (13. Jahrhundert)"],"types":["http://dbpedia.org/ontology/WrittenWork","http://dbpedia.org/ontology/Work"],"alternateLabels":["Rudolf von Güttingen"]},{"start":840,"end":845,"spot":"Landl","confidence":0.8134,"id":999054,"title":"Landl","uri":"http://de.wikipedia.org/wiki/Landl","label":"Landl","categories":["Eisenwurzen","Ennstaler Alpen","Gemeindegründung 2015","Hochschwab","Katastralgemeinde im Bezirk Liezen","Ort an der Enns","Salza (Enns)","Ybbstaler Alpen"],"types":["http://dbpedia.org/ontology/Settlement","http://dbpedia.org/ontology/PopulatedPlace","http://dbpedia.org/ontology/Place","http://dbpedia.org/ontology/Location"],"alternateLabels":["Landl"]},{"start":903,"end":907,"spot":"Embs","confidence":0.6429,"id":3469040,"title":"Embs","uri":"http://de.wikipedia.org/wiki/Embs","label":"Embs","categories":["Deutsches Adelsgeschlecht","Fränkisches Rittergeschlecht"],"types":[],"alternateLabels":["Embs"]},{"start":912,"end":919,"spot":"Randegg","confidence":0.8261,"id":482370,"title":"Randegg","uri":"http://de.wikipedia.org/wiki/Randegg","label":"Randegg","categories":["Eisenwurzen","Randegg"],"types":["http://dbpedia.org/ontology/Settlement","http://dbpedia.org/ontology/PopulatedPlace","http://dbpedia.org/ontology/Place","http://dbpedia.org/ontology/Location"],"alternateLabels":["Randegg"]},{"start":929,"end":935,"spot":"Pilger","confidence":0.7379,"id":16770,"title":"Pilger","uri":"http://de.wikipedia.org/wiki/Pilger","label":"Pilger","categories":["Personenbezeichnung (Religion)","Pilger","Spiritualität","Verkehrsteilnehmer"],"types":["http://dbpedia.org/ontology/WrittenWork","http://dbpedia.org/ontology/Work"],"alternateLabels":["Pilger","Wallfahrer","Pilgern","Wallfahrern","Pilgerung"]},{"start":942,"end":947,"spot":"Landl","confidence":0.8142,"id":999054,"title":"Landl","uri":"http://de.wikipedia.org/wiki/Landl","label":"Landl","categories":["Eisenwurzen","Ennstaler Alpen","Gemeindegründung 2015","Hochschwab","Katastralgemeinde im Bezirk Liezen","Ort an der Enns","Salza (Enns)","Ybbstaler Alpen"],"types":["http://dbpedia.org/ontology/Settlement","http://dbpedia.org/ontology/PopulatedPlace","http://dbpedia.org/ontology/Place","http://dbpedia.org/ontology/Location"],"alternateLabels":["Landl"]},{"start":966,"end":970,"spot":"Bühl","confidence":0.7441,"id":829742,"title":"Bühl BE","uri":"http://de.wikipedia.org/wiki/B%C3%BChl_BE","label":"Bühl BE","categories":["Ersterwähnung im 13. Jahrhundert","Ort im Kanton Bern","Schweizer Gemeinde"],"types":["http://dbpedia.org/ontology/Settlement","http://dbpedia.org/ontology/PopulatedPlace","http://dbpedia.org/ontology/Place","http://dbpedia.org/ontology/Location"],"alternateLabels":["Bühl","Bühl BE"]},{"start":988,"end":993,"spot":"Landl","confidence":0.8142,"id":999054,"title":"Landl","uri":"http://de.wikipedia.org/wiki/Landl","label":"Landl","categories":["Eisenwurzen","Ennstaler Alpen","Gemeindegründung 2015","Hochschwab","Katastralgemeinde im Bezirk Liezen","Ort an der Enns","Salza (Enns)","Ybbstaler Alpen"],"types":["http://dbpedia.org/ontology/Settlement","http://dbpedia.org/ontology/PopulatedPlace","http://dbpedia.org/ontology/Place","http://dbpedia.org/ontology/Location"],"alternateLabels":["Landl"]},{"start":1040,"end":1046,"spot":"Glarus","confidence":0.7934,"id":1911,"title":"Kanton Glarus","uri":"http://de.wikipedia.org/wiki/Kanton_Glarus","label":"Kanton Glarus","categories":["Kanton (Schweiz)","Kanton Glarus"],"types":["http://dbpedia.org/ontology/Place","http://dbpedia.org/ontology/Location"],"alternateLabels":["Glarus","Kanton Glarus","Kantons Glarus","Glarner","Glarnerland"]},{"start":1060,"end":1066,"spot":"Tuggen","confidence":0.7715,"id":180887,"title":"Tuggen","uri":"http://de.wikipedia.org/wiki/Tuggen","label":"Tuggen","categories":["Linthgebiet","Ort im Kanton Schwyz","Schweizer Gemeinde","Tuggen"],"types":["http://dbpedia.org/ontology/Settlement","http://dbpedia.org/ontology/PopulatedPlace","http://dbpedia.org/ontology/Place","http://dbpedia.org/ontology/Location"],"alternateLabels":["Tuggen"]}],"lang":"de","timestamp":"2024-09-06T19:51:50.690"}