{"date_folder":"1783-10", "time":18,"annotations":[{"start":116,"end":117,"spot":"£","confidence":0.6496,"id":596831,"title":"Parti Socialiste (Belgien)","uri":"http://de.wikipedia.org/wiki/Parti_Socialiste_%28Belgien%29","label":"Parti Socialiste","categories":["Gegründet 1978","Partei (Belgien)","Partei in der Deutschsprachigen Gemeinschaft","Parti Socialiste (Belgien)","Politik (Region Brüssel-Hauptstadt)","Politik (Wallonien)","Sozialdemokratische Partei","Sozialistische Partei"],"types":["http://dbpedia.org/ontology/PoliticalParty","http://dbpedia.org/ontology/Organisation","http://dbpedia.org/ontology/Agent"],"alternateLabels":["Parti Socialiste","PS","Sozialistische Partei","Sozialistischen Partei","Sozialistischer Partei"]},{"start":143,"end":148,"spot":"Halın","confidence":0.7542,"id":1661934,"title":"Halin","uri":"http://de.wikipedia.org/wiki/Halin","label":"Halin","categories":["Archäologischer Fundplatz in Asien","Archäologischer Fundplatz in Myanmar","Bestandteil der Welterbestätte „Historische Städte der Pyu“","Geschichte Myanmars","Sagaing-Region"],"types":["http://dbpedia.org/ontology/Place","http://dbpedia.org/ontology/Location"],"alternateLabels":["Halin"]},{"start":186,"end":190,"spot":"odor","confidence":0.7239,"id":2097320,"title":"Odor","uri":"http://de.wikipedia.org/wiki/Odor","label":"Odor","categories":["Riechen"],"types":[],"alternateLabels":["Odor","Odeur","Duft"]},{"start":191,"end":200,"spot":"Girtanner","confidence":0.6862,"id":10581828,"title":"Friedrich Girtanner","uri":"http://de.wikipedia.org/wiki/Friedrich_Girtanner","label":"Friedrich Girtanner","categories":["Bürgermeister (St. Gallen)","Geboren 1664","Gestorben 1753","Mann","Mitglied der Familie Girtanner","Schweizer","Tagsatzungsgesandter","Vogt (Amt)"],"types":["http://dbpedia.org/ontology/Person","http://dbpedia.org/ontology/Species","http://dbpedia.org/ontology/Eukaryote","http://dbpedia.org/ontology/Animal"],"alternateLabels":["Friedrich Girtanner"]},{"start":202,"end":204,"spot":"Hr","confidence":0.6185,"id":2768,"title":"Kroatien","uri":"http://de.wikipedia.org/wiki/Kroatien","label":"Kroatien","categories":["Kroatien","Mitglied des Europarats","Mitgliedstaat der Europäischen Union","Mitgliedstaat der NATO","Mitgliedstaat der Vereinten Nationen","Staat in Europa","Verwaltungseinheit als Namensgeber für einen Asteroiden"],"types":["http://dbpedia.org/ontology/Country","http://dbpedia.org/ontology/PopulatedPlace","http://dbpedia.org/ontology/Place","http://dbpedia.org/ontology/Location"],"alternateLabels":["Kroatien","Kroatischer","Kroatischen","Kroatische","Kroatisch"]},{"start":216,"end":225,"spot":"Schlatter","confidence":0.6265,"id":468259,"title":"Adolf Schlatter","uri":"http://de.wikipedia.org/wiki/Adolf_Schlatter","label":"Adolf Schlatter","categories":["Bibelübersetzer ins Deutsche","Evangelischer Theologe (19. Jahrhundert)","Evangelischer Theologe (20. Jahrhundert)","Geboren 1852","Gestorben 1938","Herausgeber","Hochschullehrer (Eberhard Karls Universität Tübingen)","Hochschullehrer (Humboldt-Universität zu Berlin)","Hochschullehrer (Universität Bern)","Hochschullehrer (Universität Greifswald)","Korporierter im Falkensteinerbund","Korporierter im Wingolf","Mann","Neutestamentler","Sachbuchautor (Theologie)","Sachliteratur (Theologie)","Schweizer","Systematischer Theologe"],"types":["http://dbpedia.org/ontology/Person","http://dbpedia.org/ontology/Species","http://dbpedia.org/ontology/Eukaryote","http://dbpedia.org/ontology/Animal"],"alternateLabels":["Adolf Schlatter","Schlatter"]},{"start":255,"end":265,"spot":"St, Gallen","confidence":0.7553,"id":10513,"title":"St. Gallen","uri":"http://de.wikipedia.org/wiki/St._Gallen","label":"St. Gallen","categories":["Gallus (Heiliger) als Namensgeber","Hauptort eines Kantons (Schweiz)","Hochschul- oder Universitätsstadt in der Schweiz","Ort an der Steinach (Bodensee)","Ort im Kanton St. Gallen","Ortsbild von nationaler Bedeutung im Kanton St. Gallen","Reichsstadt","Schweizer Gemeinde","St. Gallen"],"types":["http://dbpedia.org/ontology/Settlement","http://dbpedia.org/ontology/PopulatedPlace","http://dbpedia.org/ontology/Place","http://dbpedia.org/ontology/Location"],"alternateLabels":["St. Gallen","St. Galler","Stadt St. Gallen","Sankt Gallen","Stadt"]}],"lang":"de","timestamp":"2024-09-06T19:53:26.983"}