{"date_folder":"1784-05", "time":5,"annotations":[{"start":87,"end":92,"spot":"Dolle","confidence":0.6907,"id":7634274,"title":"Hans Dölle","uri":"http://de.wikipedia.org/wiki/Hans_D%C3%B6lle","label":"Hans Dölle","categories":["Deutscher","Geboren 1893","Gestorben 1980","Hochschullehrer (Eberhard Karls Universität Tübingen)","Hochschullehrer (Reichsuniversität Straßburg)","Hochschullehrer (Rheinische Friedrich-Wilhelms-Universität Bonn)","Hochschullehrer (Universität Stuttgart)","Mann","Militärperson (Heer des Deutschen Kaiserreiches)","Mitglied der Joachim-Jungius-Gesellschaft der Wissenschaften","NSDAP-Mitglied","Privatrechtler (20. Jahrhundert)","Träger des Eisernen Kreuzes I. Klasse","Wissenschaftliches Mitglied der Kaiser-Wilhelm-Gesellschaft","Wissenschaftliches Mitglied der Max-Planck-Gesellschaft"],"types":["http://dbpedia.org/ontology/Person","http://dbpedia.org/ontology/Species","http://dbpedia.org/ontology/Eukaryote","http://dbpedia.org/ontology/Animal"],"alternateLabels":["Hans Dölle"]},{"start":108,"end":112,"spot":"Thor","confidence":0.7072,"id":11621,"title":"Thor","uri":"http://de.wikipedia.org/wiki/Thor","label":"Thor","categories":["Drachentöter","Germanische Gottheit","Germanische Gottheit als Namensgeber für einen Asteroiden","Männliche Gottheit","Namensgeber für ein Schiff","Namensgeber für ein chemisches Element","Thor","Wettergottheit"],"types":["http://dbpedia.org/ontology/WrittenWork","http://dbpedia.org/ontology/Work"],"alternateLabels":["Thor","Donar","Donar/Thor","Þórr","Thor/Donar"]}],"lang":"de","timestamp":"2024-09-06T19:56:42.142"}